{
	"script" : [
		{
			"use_textbox"	: 1,
			"play_music"	: "tutorbot_scene_music",
			"bg_image"		: "spr_tutorial_common",
			"character"		: ["VOICE_bot", "CHAR_tutor_right", "MOOD_normal"],
			"dialog"		: "Этот Модуль должна прервать Ваш текущий сон, сообщив важную информацию.",
		},
		{
			"character"		: ["VOICE_bot", "CHAR_tutor_right", "MOOD_normal"],
			"dialog"		: "Сейчас Этот Модуль объяснит Вам уникальные правила |C3|битвы-Крепости.|C0|",
		},
		{
			"character"		: ["VOICE_bot", "CHAR_tutor_right", "MOOD_normal"],
			"dialog"		: "|C3|Битвы-Крепости|C0| - это особый вид |C3|робких битв|C0|, в котором Вы должны пройти через крепость монстра.",
		},
		{
			"show_tutorial"	: "combo_bar6",
			"character"		: ["VOICE_bot", "CHAR_tutor_right", "MOOD_normal"],
			"dialog"		: "|C3|Монстры-Крепости|C0| будут удерживать Ваше комбо так же, как и любой другой |C3|робкий монстр|C0|, но есть одно большое отличие.",
		},
		{
			"character"		: ["VOICE_bot", "CHAR_tutor_right", "MOOD_normal"],
			"dialog"		: "В крепостях много разрушаемых ловушек и турелей с крайне высокой защитой, но малым содержанием частиц.",
		},
		{
			"character"		: ["VOICE_bot", "CHAR_tutor_right", "MOOD_normal"],
			"dialog"		: "Вы можете спокойно позволить этим ловушкам покинуть арену, не потеряв комбо.",
		},
		{
			"character"		: ["VOICE_bot", "CHAR_tutor_right", "MOOD_normal"],
			"dialog"		: "Вашей основной задачей будет разрушение |C3|особых приспешников|C0|, охраняющих крепость.",
		},
		{
			"character"		: ["VOICE_bot", "CHAR_tutor_right", "MOOD_normal"],
			"dialog"		: "|C3|Особые приспешники|C0| будут выделяться внешним видом среди других разрушимых частей башни.",
		},
		{
			"show_tutorial"	: "combo_bar7",
			"character"		: ["VOICE_bot", "CHAR_tutor_right", "MOOD_normal"],
			"dialog"		: "Комбо исчезнет, только если |C3|особый приспешник сбежит, не получив любви.|C0|",
		},
		{
			"character"		: ["VOICE_bot", "CHAR_tutor_right", "MOOD_normal"],
			"dialog"		: "|C3|Предложение:|C0| Следите за особыми приспешниками этого монстра-крепости и не позволяйте ни одному из них сбежать.",
		},
		{
			"show_tutorial"	: "none",
			"character"		: ["VOICE_bot", "CHAR_tutor_right", "MOOD_normal"],
			"dialog"		: "Это вся информация о |C3|битвах-Крепостях,|C0| которой располагает для Вас Этот Модуль.",
		},
		{
			"love_hearts"	: 1,
			"character"		: ["VOICE_bot", "CHAR_tutor_right", "MOOD_blush"],
			"dialog"		: "У Этого Модуля наблюдается резкое повышение температуры.",
		},
		{
			"character"		: ["VOICE_bot", "CHAR_tutor_right", "MOOD_blush"],
			"dialog"		: "Не существует крепости, которая может сдержать такой напор любви.",
		}
	]
}