{
	"big_text_intro" : [
		{
			"play_music"		: "silence",
			"center_text_x"		: 1,
			"center_text_y"		: 1,
			"text_x"			: 320,
			"text_y"			: 180,
			"text_w"			: 400,
			"voice"				: "VOICE_default",
			"dialog"			: "|C3|Чуть позже,|L| в месте неподалёку.",
		},
		{
			"dialog"			: "|C3|[VAL2] случайно повстречалась с монстром. Это была...",
		},
	],
	
	"my_name"	: "Буревая Веераль",
	"my_nickname"	: "Бурька",
	
	"step1_ask_generic" : [
		{
			"character"			: ["VOICE_veyeral", "CHAR_storm_veyeral_left", "MOOD_sad"],
			"random"			: 3,
			"dialog_rand1"		: "Эмм, привет, [VAL1].|!||L|Ты занята?",
			"dialog_rand2"		: "Извини, [VAL1]. Мне, эээ, наверное, понадобится помощь.",
			"dialog_rand3"		: "Эмм, [VAL1]? Можешь помочь мне кое с чем?",
		},
		{
			"character"			: ["VOICE_veyeral", "CHAR_storm_veyeral_left", "MOOD_normal"],
			"random"			: 3,
			"dialog_rand1"		: "Значит, есть одна Зарадена, и мне надо извиниться перед ней-",
			"dialog_rand2"		: "Я поступила плохо с этой Зараденой, и мне хотелось бы извиниться перед ней.",
			"dialog_rand3"		: "Мне нужно искупить то, что я сделала с этой Зараденой-",
		},
	],
	"step1_ask_generic_twins" : [
		{
			"character"			: ["VOICE_veyeral", "CHAR_storm_veyeral_left", "MOOD_sad"],
			"random"			: 3,
			"dialog_rand1"		: "Можешь мне помочь, [VAL1]?",
			"dialog_rand2"		: "Извини, [VAL1]. Мне, эээ, наверное, понадобится помощь.",
			"dialog_rand3"		: "Эмм, [VAL1]? Можешь помочь мне кое с чем?",
		},
		{
			"character"			: ["VOICE_veyeral", "CHAR_storm_veyeral_left", "MOOD_normal"],
			"random"			: 2,
			"dialog_rand1"		: "Значит, тут были те две Зарадены-",
			"dialog_rand2"		: "Эти Зарадены-близнецы-",
		},
		{
			"character"			: ["VOICE_veyeral", "CHAR_storm_veyeral_left", "MOOD_sad"],
			"dialog"			: "Мне нужно извиниться перед ними.|L||!|Ну, в основном перед зелёной с волосами цвета солнышка.",
		},
	],
	"step1_ask_B_storm_veyeral"			: "step1_ask_self",
	"step1_ask_B_anomaly"				: "step1_ask_self",
	"step1_ask_self" : [
		{
			"character"			: ["VOICE_veyeral", "CHAR_storm_veyeral_right", "MOOD_normal"],
			"dialog"			: "Что за сила у неё была?",
		},
		{
			"character"			: ["VOICE_veyeral", "CHAR_storm_veyeral_right", "MOOD_happy"],
			"dialog"			: "|wave|Это было так хорошо.",
		},
		{
			"character"			: ["VOICE_veyeral", "CHAR_storm_veyeral_right", "MOOD_normal"],
			"dialog"			: "И теперь я чувствую себя по-другому.",
		},
		{
			"character"			: ["VOICE_veyeral", "CHAR_storm_veyeral_right", "MOOD_angry"],
			"dialog"			: "И чем я вообще думала, нападая на неё?",
		},
		{
			"character"			: ["VOICE_veyeral", "CHAR_storm_veyeral_right", "MOOD_sad"],
			"dialog"			: "...",
		},
		{
			"character"			: ["VOICE_veyeral", "CHAR_storm_veyeral_right", "MOOD_sad"],
			"dialog"			: "Мне надо извиниться.",
		},
	],
	"step1_ask_B_blot"					: "step1_ask_unknown",
	"step1_ask_B_photoxai"				: "step1_ask_unknown",
	"step1_ask_B_hematoren"				: "step1_ask_unknown",
	"step1_ask_B_ombroah"				: "step1_ask_unknown",
	"step1_ask_B_glacia"				: "step1_ask_unknown",
	"step1_ask_B_pearl"					: "step1_ask_unknown",
	"step1_ask_unknown" 	: [
		{
			"character"			: ["VOICE_veyeral", "CHAR_storm_veyeral_left", "MOOD_sad"],
			"random"			: 3,
			"dialog_rand1"		: "Я знаю, что ты не знаешь меня, но выглядишь-",
			"dialog_rand2"		: "Знаю, мы не знаем друг друга, но-",
			"dialog_rand3"		: "Ты не знаешь меня, но похоже, что-",
		},
		{
			"character"			: ["VOICE_veyeral", "CHAR_storm_veyeral_left", "MOOD_normal"],
			"random"			: 2,
			"dialog_rand1"		: "Ты встречалась сегодня с Зараденой?",
			"dialog_rand2"		: "Проиграла ли ты сегодня битву с Зараденой?",
		},
		{
			"character"			: ["VOICE_veyeral", "CHAR_storm_veyeral_left", "MOOD_sad"],
			"dialog"			: "Наверное, я была в ужасе от неё, но теперь-",
		},
	],
	"step1_ask_B_emerald"				: "step1_ask_gem",
	"step1_ask_B_ruby"					: "step1_ask_gem",
	"step1_ask_B_topaz"					: "step1_ask_gem",
	"step1_ask_B_sapphire"				: "step1_ask_gem",
	"step1_ask_B_citrine"				: "step1_ask_gem",
	"step1_ask_B_amethyst"				: "step1_ask_gem",
	"step1_ask_gem" 	: [
		{
			"character"			: ["VOICE_gem", "CHAR_gem_right", "MOOD_normal"],
			"random"			: 4,
			"dialog_rand1"		: "Не бойся Меня.",
			"dialog_rand2"		: "Не бойся Этой Сферы.",
			"dialog_rand3"		: "Не страшись Этой Сферы перед собой.",
			"dialog_rand4"		: "Этой Сферы не нужно бояться.",
		},
		{
			"character"			: ["VOICE_veyeral", "CHAR_storm_veyeral_left", "MOOD_normal"],
			"dialog"			: "|shake|Не делай мне больно!",
		},
		{
			"character"			: ["VOICE_gem", "CHAR_gem_right", "MOOD_normal"],
			"dialog"			: "Эта Сфера здесь, лишь чтобы помочь.",
		},
		{
			"character"			: ["VOICE_gem", "CHAR_gem_right", "MOOD_normal"],
			"dialog"			: "Ты доставишь благословление Зарадене, что полюбила тебя.",
		},
		{
			"character"			: ["VOICE_veyeral", "CHAR_storm_veyeral_left", "MOOD_normal"],
			"dialog"			: "Откуда ты об этом узнала?",
		},
		{
			"character"			: ["VOICE_gem", "CHAR_gem_right", "MOOD_normal"],
			"dialog"			: "Она чувствует сильный эмоциональный материал внутри тебя.",
		},
	],
	"step1_ask_B_emerald_twins"			: "step1_ask_gem_extra",
	"step1_ask_B_ruby_devil"			: "step1_ask_gem_extra",
	"step1_ask_B_topaz_twins"			: "step1_ask_gem_extra",
	"step1_ask_B_citrine_blank"			: "step1_ask_gem_extra",
	"step1_ask_B_amethyst_defect"		: "step1_ask_gem_extra",
	"step1_ask_gem_extra" 	: [
		{
			"character"			: ["VOICE_gem", "CHAR_gem_right", "MOOD_normal"],
			"dialog"			: "Она чувствует сильный эмоциональный материал внутри тебя.",
		},
		{
			"character"			: ["VOICE_gem", "CHAR_gem_right", "MOOD_normal"],
			"dialog"			: "Ты доставишь благословление Зарадене, что полюбила тебя.",
		},
		{
			"character"			: ["VOICE_veyeral", "CHAR_storm_veyeral_left", "MOOD_sad"],
			"dialog"			: "Но как ты об этом узнала?",
		},
		{
			"character"			: ["VOICE_gem", "CHAR_gem_right", "MOOD_normal"],
			"dialog"			: "Эта Сфера испытывает сильный резонанс с Зараденой, что полюбила тебя.",
		},
		{
			"character"			: ["VOICE_gem", "CHAR_gem_right", "MOOD_normal"],
			"dialog"			: "Ты несёшь в себе этот сильный эмоциональный материал.",
		},
		{
			"character"			: ["VOICE_veyeral", "CHAR_storm_veyeral_left", "MOOD_normal"],
			"dialog"			: "Это хорошо?",
		},
		{
			"character"			: ["VOICE_gem", "CHAR_gem_right", "MOOD_normal"],
			"dialog"			: "Необходимо знать, что Она будет обладать дополнительными благословениями на выбор.",
		},
		{
			"character"			: ["VOICE_gem", "CHAR_gem_right", "MOOD_normal"],
			"dialog"			: "Выбирай дар с умом.",
		},
	],
	
	
	
	"step1_leave_generic" : [
		{
			"character"			: ["VOICE_veyeral", "CHAR_storm_veyeral_left", "MOOD_happy"],
			"random"			: 3,
			"dialog_rand1"		: "Спасибо тебе!|L||!|Я отнесу это ей прямо сейчас.",
			"dialog_rand2"		: "Я удостоверюсь, что она получит это!",
			"dialog_rand3"		: "Я доставлю ей это прямо сейчас!",
		},
	],
	"step1_leave_generic_twins" : [
		{
			"character"			: ["VOICE_veyeral", "CHAR_storm_veyeral_left", "MOOD_happy"],
			"random"			: 2,
			"dialog_rand1"		: "Я удостоверюсь, что они получат это!",
			"dialog_rand2"		: "Я доставлю им это прямо сейчас!",
		},
	],
	"step1_leave_B_storm_veyeral"		: "step1_leave_self",
	"step1_leave_B_anomaly"				: "step1_leave_self",
	"step1_leave_self" : [
		{
			"character"			: ["VOICE_veyeral", "CHAR_storm_veyeral_right", "MOOD_normal"],
			"dialog"			: "Надеюсь, она найдёт в своём сердце силы простить меня.",
		},
	],
	"step1_leave_self_twins" : [
		{
			"character"			: ["VOICE_veyeral", "CHAR_storm_veyeral_right", "MOOD_normal"],
			"dialog"			: "Её сестра выглядела так, будто тоже готова напасть на меня.",
		},
		{
			"character"			: ["VOICE_veyeral", "CHAR_storm_veyeral_right", "MOOD_sad"],
			"dialog"			: "Надеюсь, они смогут меня простить.",
		},
	],
	"step1_leave_B_blot"				: "step1_leave_unknown",
	"step1_leave_B_amalga"				: "step1_leave_unknown",
	"step1_leave_B_photoxai"			: "step1_leave_unknown",
	"step1_leave_B_hematoren"			: "step1_leave_unknown",
	"step1_leave_B_ombroah"				: "step1_leave_unknown",
	"step1_leave_B_hadesoh"				: "step1_leave_unknown",
	"step1_leave_B_unit_lulu"			: "step1_leave_unknown",
	"step1_leave_B_null_unit"			: "step1_leave_unknown",
	"step1_leave_B_prisma"				: "step1_leave_unknown",
	"step1_leave_B_syncron"				: "step1_leave_unknown",
	"step1_leave_B_flip_flap"			: "step1_leave_unknown",
	"step1_leave_B_sentinel_4x"			: "step1_leave_unknown",
	"step1_leave_B_glacia"				: "step1_leave_unknown",
	"step1_leave_B_momo"				: "step1_leave_unknown",
	"step1_leave_unknown" 	: [
		{
			"character"			: ["VOICE_veyeral", "CHAR_storm_veyeral_left", "MOOD_happy"],
			"dialog"			: "Спасибо тебе большое за это!",
		},
		{
			"character"			: ["VOICE_veyeral", "CHAR_storm_veyeral_left", "MOOD_normal"],
			"dialog"			: "Было приятно с тобой встретиться.|L||!|Кстати, я - [VAL2].",
		},
	],
	"step1_leave_B_lila"				: "step1_leave_eyeball",
	"step1_leave_B_split_veyeral"		: "step1_leave_eyeball",
	"step1_leave_B_burning_veyeral"		: "step1_leave_eyeball",
	"step1_leave_B_voltage_veyeral"		: "step1_leave_eyeball",
	"step1_leave_B_venom_veyeral"		: "step1_leave_eyeball",
	"step1_leave_B_frozen_veyeral"		: "step1_leave_eyeball",
	"step1_leave_B_vibrant_veyeral"		: "step1_leave_eyeball",
	"step1_leave_B_veyeral_rain"		: "step1_leave_eyeball",
	"step1_leave_B_molten_veyeral"		: "step1_leave_eyeball",
	"step1_leave_eyeball" 	: [
		{
			"character"			: ["VOICE_veyeral", "CHAR_storm_veyeral_left", "MOOD_happy"],
			"dialog"			: "Спасибо тебе большое за это!",
		},
		{
			"character"			: ["VOICE_veyeral", "CHAR_storm_veyeral_left", "MOOD_happy"],
			"dialog"			: "|wave|Глаз видит вас!",
		},
	],
	"step1_leave_B_emerald"				: "step1_leave_gem",
	"step1_leave_B_ruby"				: "step1_leave_gem",
	"step1_leave_B_topaz"				: "step1_leave_gem",
	"step1_leave_B_sapphire"			: "step1_leave_gem",
	"step1_leave_B_citrine"				: "step1_leave_gem",
	"step1_leave_B_amethyst"			: "step1_leave_gem",
	"step1_leave_gem" 	: [
		{
			"character"			: ["VOICE_veyeral", "CHAR_storm_veyeral_left", "MOOD_sad"],
			"dialog"			: "А если ей не захочется меня видеть?",
		},
		{
			"character"			: ["VOICE_gem", "CHAR_gem_right", "MOOD_normal"],
			"dialog"			: "Ты доставишь благословление Зарадене, и тогда ты поймёшь.",
		},
		{
			"character"			: ["VOICE_veyeral", "CHAR_storm_veyeral_left", "MOOD_sad"],
			"dialog"			: "Ээм, хорошо. Я попробую.",
		},
		{
			"character"			: ["VOICE_veyeral", "CHAR_storm_veyeral_left", "MOOD_normal"],
			"dialog"			: "Аааа, а кто ты?",
		},
		{
			"character"			: ["VOICE_gem", "CHAR_gem_right", "MOOD_normal"],
			"dialog"			: "Сфера пред тобой - просто [VAL1],    Сфера пред тобой.",
		},
	],
	
	
	
	"step1_ask_B_scrambla_defect" : [
		{
			"character"			: ["VOICE_veyeral", "CHAR_storm_veyeral_left", "MOOD_sad"],
			"dialog"			: "А, [VAL1], ты знаешь эту Зарадену с красными глазами?",
		},
		{
			"character"			: ["VOICE_scrambla", "CHAR_scrambla_right", "MOOD_blush"],
			"dialog"			: "Мы... знаем эту Зарадену.",
		},
		{
			"character"			: ["VOICE_veyeral", "CHAR_storm_veyeral_left", "MOOD_sad"],
			"dialog"			: "Я типа напала на неё ранее, и-",
		},
		{
			"character"			: ["VOICE_veyeral", "CHAR_storm_veyeral_left", "MOOD_normal"],
			"dialog"			: "[VAL1], ты в порядке?",
		},
		{
			"character"			: ["VOICE_scrambla", "CHAR_scrambla_right", "MOOD_blush"],
			"dialog"			: "Эмм...",
		},
		{
			"character"			: ["VOICE_scrambla", "CHAR_scrambla_right", "MOOD_despair"],
			"dialog"			: "|shake|Мы не знаем!|norm||!||L|От этой Зарадены мы чувствуим себя странно!",
		},
		{
			"character"			: ["VOICE_scrambla", "CHAR_scrambla_right", "MOOD_sad"],
			"dialog"			: "От неё нам грустно, и как будто мы хотим... чего-то?",
		},
		{
			"character"			: ["VOICE_veyeral", "CHAR_storm_veyeral_left", "MOOD_happy"],
			"dialog"			: "Ты хочешь    дать ей что-то?",
		},
		{
			"character"			: ["VOICE_scrambla", "CHAR_scrambla_right", "MOOD_happy_blush"],
			"dialog"			: "Да!    Но нам страшно это сделать.",
		},
		{
			"character"			: ["VOICE_veyeral", "CHAR_storm_veyeral_left", "MOOD_happy"],
			"dialog"			: "А если я передам это за тебя?",
		},
		{
			"character"			: ["VOICE_veyeral", "CHAR_storm_veyeral_left", "MOOD_normal"],
			"dialog"			: "Как насчёт этого?",
		},
		{
			"character"			: ["VOICE_scrambla", "CHAR_scrambla_right", "MOOD_happy"],
			"dialog"			: "Оки!",
		},
	],
	"step1_leave_B_scrambla_defect" : [
		{
			"character"			: ["VOICE_veyeral", "CHAR_storm_veyeral_left", "MOOD_normal"],
			"dialog"			: "Я скажу ей, что это от тебя, окей?",
		},
		{
			"character"			: ["VOICE_scrambla", "CHAR_scrambla_right", "MOOD_blush"],
			"dialog"			: "Эмм... Да, оки.",
		},
		{
			"character"			: ["VOICE_veyeral", "CHAR_storm_veyeral_left", "MOOD_happy"],
			"dialog"			: "Спорим, ей понравится.",
		},
		{
			"love_hearts"		: 1,
			"character"			: ["VOICE_scrambla", "CHAR_scrambla_right", "MOOD_happy_blush"],
			"dialog"			: "Мы спрячимся в этом уголке навечно, оки?",
		},
	],
	
	"step1_ask_B_knot_knott" : [
		{
			"character"			: ["VOICE_knott", "CHAR_knott_right", "MOOD_sad"],
			"dialog"			: "Значит, ты правда хочешь, чтобы она простила тебя?",
		},
		{
			"character"			: ["VOICE_veyeral", "CHAR_storm_veyeral_left", "MOOD_sad"],
			"dialog"			: "Да, я действительно хочу.",
		},
		{
			"character"			: ["VOICE_knot", "CHAR_knot_right", "MOOD_surprised"],
			"dialog"			: "Тогда просто сделай то же, что и мы, когда сражаемся.",
		},
		{
			"character"			: ["VOICE_knott", "CHAR_knott_right", "MOOD_happy"],
			"dialog"			: "Тебе нужно будет принести ей дары.",
		},
	],
	
	"step1_ask_B_amalga" 	: [
		{
			"character"			: ["VOICE_veyeral", "CHAR_storm_veyeral_left", "MOOD_sad"],
			"dialog"			: "Я знаю, ты меня не знаешь, но я тут думала-",
		},
		{
			"character"			: ["VOICE_veyeral", "CHAR_storm_veyeral_left", "MOOD_normal"],
			"dialog"			: "Мне кажется, ты встречала сегодня Зарадену?",
		},
		{
			"character"			: ["VOICE_amalga", "CHAR_amalga_right", "MOOD_surprised"],
			"dialog"			: "Бедняжка!",
		},
		{
			"character"			: ["VOICE_amalga", "CHAR_amalga_right", "MOOD_sad"],
			"dialog"			: "С тобой всё в порядке? Выглядишь измождённо!",
		},
		{
			"character"			: ["VOICE_veyeral", "CHAR_storm_veyeral_left", "MOOD_sad"],
			"dialog"			: "Нууу, мне грустно за моё прошлое поведение.",
		},
		{
			"character"			: ["VOICE_amalga", "CHAR_amalga_right", "MOOD_happy"],
			"dialog"			: "О, Зарадена простит тебя, мы уверены!",
		},
		{
			"character"			: ["VOICE_amalga", "CHAR_amalga_right", "MOOD_sad"],
			"dialog"			: "Но она вечно попадает в драки, и мы беспокоимся.",
		},
		{
			"character"			: ["VOICE_amalga", "CHAR_amalga_right", "MOOD_surprised"],
			"dialog"			: "Тебе надо передать ей дар, и ты увидишь, что тебя простят.",
		},
	],
	
	"step1_ask_B_heliola" : [
		{
			"character"			: ["VOICE_veyeral", "CHAR_storm_veyeral_left", "MOOD_normal"],
			"dialog"			: "Не прячешься сегодня?",
		},
		{
			"character"			: ["VOICE_heliola", "CHAR_heliola_right", "MOOD_happy"],
			"dialog"			: "Ни в коем случае, звёздочка!",
		},
		{
			"character"			: ["VOICE_heliola", "CHAR_heliola_right", "MOOD_sparkle1"],
			"dialog"			: "То время уже прошло!",
		},
		{
			"character"			: ["VOICE_heliola", "CHAR_heliola_right", "MOOD_sparkle2"],
			"dialog"			: "Миру нужен мой звёздный свет!",
		},
		{
			"character"			: ["VOICE_heliola", "CHAR_heliola_right", "MOOD_surprised"],
			"dialog"			: "Точно так, будто бы сейчас тебе не помешало немного звёздного света.",
		},
		{
			"character"			: ["VOICE_veyeral", "CHAR_storm_veyeral_left", "MOOD_sad"],
			"dialog"			: "Я думаю, мне нужно извиниться перед Зараденой.",
		},
		{
			"character"			: ["VOICE_heliola", "CHAR_heliola_right", "MOOD_confused"],
			"dialog"			: "О, она и тебя достала?",
		},
		{
			"character"			: ["VOICE_heliola", "CHAR_heliola_right", "MOOD_happy"],
			"dialog"			: "Просто дай ей это!",
		},
	],
	"step1_ask_B_heliola_twins" : [
		{
			"character"			: ["VOICE_heliola", "CHAR_heliola_right", "MOOD_starstruck"],
			"dialog"			: "Так ты тоже встретила близняшек Зараден?",
		},
		{
			"character"			: ["VOICE_heliola", "CHAR_heliola_right", "MOOD_content_blush"],
			"dialog"			: "О. Мои. Звёзды. Ты видела то Солнышко?",
		},
		{
			"character"			: ["VOICE_heliola", "CHAR_heliola_right", "MOOD_awkward"],
			"dialog"			: "|shake|Я схожу с ума.",
		},
		{
			"character"			: ["VOICE_veyeral", "CHAR_storm_veyeral_left", "MOOD_normal"],
			"dialog"			: "Ну, я хотела пойти извиниться за моё поведение.",
		},
		{
			"character"			: ["VOICE_veyeral", "CHAR_storm_veyeral_left", "MOOD_happy"],
			"dialog"			: "Хочешь ей что-то передать?",
		},
		{
			"character"			: ["VOICE_heliola", "CHAR_heliola_right", "MOOD_sparkle2"],
			"dialog"			: "А ты передашь?!",
		},
	],
	"step1_leave_B_heliola_twins" : [
		{
			"character"			: ["VOICE_veyeral", "CHAR_storm_veyeral_left", "MOOD_normal"],
			"dialog"			: "Я передам ей, что это от тебя, окей?",
		},
		{
			"character"			: ["VOICE_heliola", "CHAR_heliola_right", "MOOD_sparkle2"],
			"dialog"			: "Расскажи мне, что она ответит!",
		},
		{
			"character"			: ["VOICE_heliola", "CHAR_heliola_right", "MOOD_pain"],
			"dialog"			: "|shake|Нет, не говори мне!",
		},
		{
			"character"			: ["VOICE_heliola", "CHAR_heliola_right", "MOOD_awkward"],
			"dialog"			: "|shake|Я сошла с ума.",
		},
	],
	
	"step1_ask_B_hadesoh" : [
		{
			"character"			: ["VOICE_hadesoh", "CHAR_hadesoh_right", "MOOD_surprised"],
			"dialog"			: "Эй, у меня есть вопрос.",
		},
		{
			"character"			: ["VOICE_hadesoh", "CHAR_hadesoh_right", "MOOD_confused"],
			"dialog"			: "Ты видишь эти дары?",
		},
		{
			"character"			: ["VOICE_veyeral", "CHAR_storm_veyeral_left", "MOOD_normal"],
			"dialog"			: "Да, но, типа, они выглядят как-то странно.",
		},
		{
			"character"			: ["VOICE_hadesoh", "CHAR_hadesoh_right", "MOOD_aggressive"],
			"dialog"			: "Это |shake||nu||ze||nah||norm| благословления!",
		},
		{
			"character"			: ["VOICE_hadesoh", "CHAR_hadesoh_right", "MOOD_happy"],
			"dialog"			: "И они - от всех нас!",
		},
		{
			"character"			: ["VOICE_veyeral", "CHAR_storm_veyeral_left", "MOOD_normal"],
			"dialog"			: "Почему я их раньше никогда их не видела?",
		},
		{
			"character"			: ["VOICE_hadesoh", "CHAR_hadesoh_right", "MOOD_normal"],
			"dialog"			: "Немногие из нас видели их раньше, но сегодня я заметила всё больше монстров, реагирующих на них.",
		},
		{
			"character"			: ["VOICE_hadesoh", "CHAR_hadesoh_right", "MOOD_aggressive"],
			"dialog"			: "Это ведь Зарадена влезла в твоё |shake||nu||ze||nah||norm| сознание, да?",
		},
		{
			"character"			: ["VOICE_veyeral", "CHAR_storm_veyeral_left", "MOOD_happy"],
			"dialog"			: "Вот почему я могу их видеть?",
		},
		{
			"character"			: ["VOICE_hadesoh", "CHAR_hadesoh_right", "MOOD_confused"],
			"dialog"			: "Я точно не уверена, и на некоторых монстров это не сработало.",
		},
		{
			"character"			: ["VOICE_hadesoh", "CHAR_hadesoh_right", "MOOD_happy"],
			"dialog"			: "Отнеси одно из этих благословлений Зарадене.",
		},
		{
			"character"			: ["VOICE_hadesoh", "CHAR_hadesoh_right", "MOOD_aggressive"],
			"dialog"			: "Ты ищешь предлог, чтобы с ней снова встретиться, по глазу видно.",
		},
	],
	
	"step1_ask_B_astrayo_twins" : [
		{
			"fast_text"			: 1,
			"character"			: ["VOICE_astrayo", "CHAR_astrayo_right", "MOOD_very_happy"],
			"dialog"			: "Ой. Ой. Ой. Ой. Ой.|L|Нет. Нет. Нет. Нет. Нет. Нет. Нет.|L|Нет. Нет. Нет. Нет. Нет. Нет.",
		},
		{
			"character"			: ["VOICE_astrayo", "CHAR_astrayo_right", "MOOD_surprised"],
			"dialog"			: "Ты встретила этих близняшек-Зараден, да?",
		},
		{
			"character"			: ["VOICE_astrayo", "CHAR_astrayo_right", "MOOD_confused"],
			"dialog"			: "Та, что с пятнышками и волосами...",
		},
		{
			"character"			: ["VOICE_astrayo", "CHAR_astrayo_right", "MOOD_blush"],
			"dialog"			: "|shake|Она такая красивая.|L|Она слишком красивая.",
		},
		{
			"character"			: ["VOICE_astrayo", "CHAR_astrayo_right", "MOOD_surprised_blush"],
			"dialog"			: "И её сестра смотрела на меня, ну, ты знаешь? Ты знаешь? Ты знаешь? Ты знаешь?",
		},
		{
			"fast_text"			: 0,
			"character"			: ["VOICE_astrayo", "CHAR_astrayo_right", "MOOD_surprised_blush"],
			"dialog"			: "|shake|Понимаешь, что я говорю!?",
		},
		{
			"character"			: ["VOICE_veyeral", "CHAR_storm_veyeral_left", "MOOD_normal"],
			"dialog"			: "|shake|[VAL1]!|norm| Ты слишком спешишь, даже для тебя!",
		},
		{
			"character"			: ["VOICE_veyeral", "CHAR_storm_veyeral_left", "MOOD_normal"],
			"dialog"			: "Что не так?",
		},
		{
			"character"			: ["VOICE_astrayo", "CHAR_astrayo_right", "MOOD_angry_blush"],
			"dialog"			: "Аргх! Просто отдай ей дары!",
		},
	],
	"step1_leave_B_astrayo_blank" : [
		{
			"character"			: ["VOICE_astrayo", "CHAR_astrayo_right", "MOOD_normal"],
			"dialog"			: "Теперь передай его ей.|L|Иди! Иди! Иди!",
		},
		{
			"fast_text"			: 1,
			"character"			: ["VOICE_veyeral", "CHAR_storm_veyeral_left", "MOOD_happy"],
			"dialog"			: "Спасибо-",
		},
		{
			"character"			: ["VOICE_astrayo", "CHAR_astrayo_right", "MOOD_happy"],
			"dialog"			: "Пока-пока, [VAL3]!",
		},
		{
			"fast_text"			: 0,
			"character"			: ["VOICE_astrayo", "CHAR_astrayo_right", "MOOD_very_happy"],
			"dialog"			: "|shake|Я ЛЮБЛЮ ТЕБЯ!",
		},
		{
			"character"			: ["VOICE_astrayo", "CHAR_astrayo_right", "MOOD_blush"],
			"dialog"			: "Это меня она научила.",
		},
		{
			"character"			: ["VOICE_veyeral", "CHAR_storm_veyeral_left", "MOOD_sad"],
			"dialog"			: "На неё это похоже.",
		},
	],
	"step1_leave_B_astrayo_twins" : [
		{
			"character"			: ["VOICE_veyeral", "CHAR_storm_veyeral_left", "MOOD_happy"],
			"dialog"			: "|wave|Мне кажется, я знаю, что происходит.",
		},
		{
			"fast_text"			: 1,
			"character"			: ["VOICE_astrayo", "CHAR_astrayo_right", "MOOD_angry_blush"],
			"dialog"			: "|shake|Стой. Стой. Стой. Стой. Стой. Стой. Стой. Стой. Стой. Стой.",
		},
		{
			"fast_text"			: 0,
			"character"			: ["VOICE_veyeral", "CHAR_storm_veyeral_left", "MOOD_normal"],
			"dialog"			: "Извини.",
		},
		{
			"love_hearts"		: 1,
			"character"			: ["VOICE_astrayo", "CHAR_astrayo_right", "MOOD_blush"],
			"dialog"			: "Просто отдай их ей, пожалуйста.",
		},
		{
			"character"			: ["VOICE_veyeral", "CHAR_storm_veyeral_left", "MOOD_happy"],
			"dialog"			: "Уже иду!",
		},
	],
	
	"step1_ask_B_philolu" : [
		{
			"character"			: ["VOICE_philolu", "CHAR_philolu_right", "MOOD_normal"],
			"dialog"			: "|wave|Эй, дорогуша.",
		},
		{
			"character"			: ["VOICE_philolu", "CHAR_philolu_right", "MOOD_happy"],
			"dialog"			: "Сделаешь кое-что для меня?",
		},
		{
			"character"			: ["VOICE_veyeral", "CHAR_storm_veyeral_left", "MOOD_normal"],
			"dialog"			: "Эм, что именно?",
		},
		{
			"character"			: ["VOICE_philolu", "CHAR_philolu_right", "MOOD_very_happy"],
			"dialog"			: "|wave|Не будь такой стесняшкой, дорогуша.",
		},
		{
			"character"			: ["VOICE_philolu", "CHAR_philolu_right", "MOOD_aggressive"],
			"dialog"			: "Эта Зарадена достала тебя, не так ли?",
		},
		{
			"character"			: ["VOICE_philolu", "CHAR_philolu_right", "MOOD_blush"],
			"dialog"			: "Мне нужно, чтобы ты передала ей что-нибудь для меня.",
		},
		{
			"character"			: ["VOICE_veyeral", "CHAR_storm_veyeral_left", "MOOD_sad"],
			"dialog"			: "Но она же больше не хочет меня видеть.",
		},
		{
			"character"			: ["VOICE_philolu", "CHAR_philolu_right", "MOOD_angry"],
			"dialog"			: "Не могу поверить, что ты такое говоришь.",
		},
		{
			"character"			: ["VOICE_philolu", "CHAR_philolu_right", "MOOD_confused"],
			"dialog"			: "Разве ты не знаешь, что она любит тебя?",
		},
		{
			"character"			: ["VOICE_veyeral", "CHAR_storm_veyeral_left", "MOOD_sad"],
			"dialog"			: "Этим утром, я даже не знала, что такое любовь.",
		},
		{
			"character"			: ["VOICE_veyeral", "CHAR_storm_veyeral_left", "MOOD_normal"],
			"dialog"			: "Это всё ещё слишком в новинку для меня.",
		},
		{
			"character"			: ["VOICE_thought", "CHAR_philolu_right", "MOOD_sad"],
			"dialog"			: "|C3|(Я так старалась сама достучаться до всех вас)",
		},
		{
			"character"			: ["VOICE_philolu", "CHAR_philolu_right", "MOOD_content"],
			"dialog"			: "Так, она дала тебе почувствовать что-то новое!",
		},
		{
			"character"			: ["VOICE_philolu", "CHAR_philolu_right", "MOOD_blush"],
			"dialog"			: "Она в самом деле замечательная, не так ли?",
		},
		{
			"character"			: ["VOICE_veyeral", "CHAR_storm_veyeral_left", "MOOD_happy"],
			"dialog"			: "Ага! Я поняла. Отнесу ей твой подарок.",
		},
	],
	"step1_leave_B_philolu" : [
		{
			"character"			: ["VOICE_veyeral", "CHAR_storm_veyeral_left", "MOOD_normal"],
			"dialog"			: "Я все еще пытаюсь понять, как работает любовь.",
		},
		{
			"character"			: ["VOICE_veyeral", "CHAR_storm_veyeral_left", "MOOD_normal"],
			"dialog"			: "Думаю, я поняла, что ты здесь делаешь.",
		},
		{
			"character"			: ["VOICE_veyeral", "CHAR_storm_veyeral_left", "MOOD_happy"],
			"dialog"			: "Больше тебе спасибо, Филолу.",
		},
		{
			"character"			: ["VOICE_philolu", "CHAR_philolu_right", "MOOD_aggressive"],
			"dialog"			: "Только теперь не раскрывай всем мои секреты.",
		},
	],
	
	"step1_ask_B_unit_lulu" : [
		{
			"character"			: ["VOICE_bot", "CHAR_tutor_right", "MOOD_normal"],
			"dialog"			: "Этот Модуль обнаружила монстра с очень низким уровнем страха.",
		},
		{
			"character"			: ["VOICE_bot", "CHAR_tutor_right", "MOOD_normal"],
			"dialog"			: "Посетила ли Вас сегодня Зарадена?",
		},
		{
			"character"			: ["VOICE_veyeral", "CHAR_storm_veyeral_left", "MOOD_normal"],
			"dialog"			: "Да, это так. Откуда ты знаешь?",
		},
		{
			"character"			: ["VOICE_veyeral", "CHAR_storm_veyeral_left", "MOOD_sad"],
			"dialog"			: "Ты знаешь её?",
		},
		{
			"character"			: ["VOICE_bot", "CHAR_tutor_right", "MOOD_normal"],
			"dialog"			: "Это возможно. Этот Модуль обучила нескольких Зараден Силе Любви.",
		},
		{
			"character"			: ["VOICE_veyeral", "CHAR_storm_veyeral_left", "MOOD_normal"],
			"dialog"			: "Так вот что это было?",
		},
		{
			"character"			: ["VOICE_veyeral", "CHAR_storm_veyeral_left", "MOOD_happy"],
			"dialog"			: "|wave|Это было прекрасное чувство.",
		},
		{
			"character"			: ["VOICE_veyeral", "CHAR_storm_veyeral_left", "MOOD_sad"],
			"dialog"			: "Но теперь мне стыдно из-за своего поведения.",
		},
		{
			"character"			: ["VOICE_bot", "CHAR_tutor_right", "MOOD_normal"],
			"dialog"			: "Этот Модуль предлагает решение, которое поможет избавиться от негативных эмоций.",
		},
		{
			"character"			: ["VOICE_bot", "CHAR_tutor_right", "MOOD_normal"],
			"dialog"			: "|C3|Предложение:|C0| Принесите Зарадене дар.",
		},
		{
			"character"			: ["VOICE_bot", "CHAR_tutor_right", "MOOD_normal"],
			"dialog"			: "Этот Модуль собрала коллекцию даров на выбор.",
		},
	],
	
	"step1_ask_B_null_unit" : [
		{
			"character"			: ["VOICE_veyeral", "CHAR_storm_veyeral_left", "MOOD_sad"],
			"dialog"			: "Ты не навредишь мне, да?",
		},
		{
			"character"			: ["VOICE_null_bot", "CHAR_null_unit_right", "MOOD_normal"],
			"dialog"			: "Я, типа, совсем не делаю таких вещей.",
		},
		{
			"character"			: ["VOICE_null_bot", "CHAR_null_unit_right", "MOOD_normal"],
			"dialog"			: "Но вообще, типа, ты    слишком вежлива для Порождения Пустоты.",
		},
		{
			"character"			: ["VOICE_null_bot", "CHAR_null_unit_right", "MOOD_normal"],
			"dialog"			: "Она, типа, и тебя достала, точняк.",
		},
		{
			"character"			: ["VOICE_veyeral", "CHAR_storm_veyeral_left", "MOOD_normal"],
			"dialog"			: "Так ты тоже встретила Зарадену!|L|Я так и знала!",
		},
		{
			"character"			: ["VOICE_null_bot", "CHAR_null_unit_right", "MOOD_normal"],
			"dialog"			: "Ты прям чувствуешь себя, типа, виновной после атаки на неё.",
		},
		{
			"character"			: ["VOICE_veyeral", "CHAR_storm_veyeral_left", "MOOD_normal"],
			"dialog"			: "|shake|Ты можешь читать мысли?",
		},
		{
			"character"			: ["VOICE_null_bot", "CHAR_null_unit_right", "MOOD_normal"],
			"dialog"			: "Неа. Я просто типа, чувствую так же.",
		},
		{
			"character"			: ["VOICE_null_bot", "CHAR_null_unit_right", "MOOD_normal"],
			"dialog"			: "Но, мне кажется, Зарадены принимают мусор в качестве извинений.",
		},
		{
			"character"			: ["VOICE_null_bot", "CHAR_null_unit_right", "MOOD_normal"],
			"dialog"			: "Дай ей немного моего мусора как дар, или типа того.",
		},
	],
	"step1_ask_B_null_unit_twins" : [
		{
			"character"			: ["VOICE_null_bot", "CHAR_null_unit_right", "MOOD_normal"],
			"dialog"			: "Не могу поверить, что мы сегодня напали, типа, на одних и тех же Зараден.",
		},
		{
			"character"			: ["VOICE_veyeral", "CHAR_storm_veyeral_left", "MOOD_normal"],
			"dialog"			: "Но что мы должны делать с этим?",
		},
		{
			"character"			: ["VOICE_null_bot", "CHAR_null_unit_right", "MOOD_normal"],
			"dialog"			: "Всё, типа, будет в порядке.",
		},
		{
			"character"			: ["VOICE_null_bot", "CHAR_null_unit_right", "MOOD_normal"],
			"dialog"			: "Мне кажется, Зарадены принимают, типа, мусор в качестве извинений, или типа того.",
		},
		{
			"character"			: ["VOICE_null_bot", "CHAR_null_unit_right", "MOOD_normal"],
			"dialog"			: "Просто дай им немного моего мусора как дар.",
		},
	],
	
	"step1_ask_B_prisma" : [
		{
			"character"			: ["VOICE_veyeral", "CHAR_storm_veyeral_left", "MOOD_sad"],
			"dialog"			: "Ты меня убьёшь, да?",
		},
		{
			"character"			: ["VOICE_prisma", "CHAR_prisma_right", "MOOD_sad"],
			"dialog"			: "Этот модуль не выявила угрозы от данного порождения Пустоты.",
		},
		{
			"character"			: ["VOICE_prisma", "CHAR_prisma_right", "MOOD_normal"],
			"dialog"			: "Многие мыслительные процессы этого модуля изменились после встречи с Зараденой.",
		},
		{
			"character"			: ["VOICE_prisma", "CHAR_prisma_right", "MOOD_sad"],
			"dialog"			: "Этот модуль обнаружила разделённое чувство скорби между нами.",
		},
		{
			"character"			: ["VOICE_veyeral", "CHAR_storm_veyeral_left", "MOOD_sad"],
			"dialog"			: "Да, Я тоже атаковала её ранее.",
		},
		{
			"character"			: ["VOICE_prisma", "CHAR_prisma_right", "MOOD_happy"],
			"dialog"			: "Этот модуль сформулировала план!",
		},
		{
			"character"			: ["VOICE_prisma", "CHAR_prisma_right", "MOOD_normal"],
			"dialog"			: "Этот Модуль отсканировал все простые дары, которые Зарадена получила сегодня.",
		},
		{
			"character"			: ["VOICE_prisma", "CHAR_prisma_right", "MOOD_happy"],
			"dialog"			: "Используя твоё высокое выделение энергии, возможно использовать дубликатор для создания даров для Зарадены!",
		},
	],
	
	"step1_ask_B_syncron" : [
		{
			"character"			: ["VOICE_syncron", "CHAR_syncr_right", "MOOD_normal"],
			"dialog"			: "Эти Модули сформулировали решение Вашей проблемы.",
		},
		{
			"character"			: ["VOICE_veyeral", "CHAR_storm_veyeral_left", "MOOD_normal"],
			"dialog"			: "И каково оно?",
		},
		{
			"character"			: ["VOICE_syncron", "CHAR_syncb_right", "MOOD_normal"],
			"dialog"			: "Вы отдадите дар обиженной вами Зарадене.",
		},
		{
			"character"			: ["VOICE_veyeral", "CHAR_storm_veyeral_left", "MOOD_sad"],
			"dialog"			: "Но у меня ничего не осталось.",
		},
		{
			"character"			: ["VOICE_syncron", "CHAR_syncr_right", "MOOD_happy"],
			"dialog"			: "Можете использовать излишнюю панику, сгенерированную Этими Модулями, как дар.",
		},
	],
	"step1_leave_B_syncron" : [
		{
			"character"			: ["VOICE_veyeral", "CHAR_storm_veyeral_left", "MOOD_happy"],
			"dialog"			: "Спасибо, что не попытались убить меня сегодня!",
		},
		{
			"character"			: ["VOICE_syncron", "CHAR_syncb_right", "MOOD_sad"],
			"dialog"			: "Эти Модули узнали, что теперь Порождения Пустоты - друзья.",
		},
		{
			"character"			: ["VOICE_veyeral", "CHAR_storm_veyeral_left", "MOOD_happy"],
			"dialog"			: "Не расстраивайтесь.",
		},
		{
			"character"			: ["VOICE_veyeral", "CHAR_storm_veyeral_left", "MOOD_angry"],
			"dialog"			: "Мы все раньше были ужасными.",
		},
	],
	"step1_leave_B_syncron_defect" : [
		{
			"character"			: ["VOICE_veyeral", "CHAR_storm_veyeral_left", "MOOD_happy"],
			"dialog"			: "Спасибо, что не попытались убить меня сегодня!",
		},
		{
			"character"			: ["VOICE_syncron", "CHAR_syncb_right", "MOOD_sad"],
			"dialog"			: "Эти Модули познали многое от Порождения Пустоты, известной как Синяя.",
		},
		{
			"character"			: ["VOICE_syncron", "CHAR_syncr_right", "MOOD_happy"],
			"dialog"			: "Больше не нужды в насилии меж нами.",
		},
		{
			"character"			: ["VOICE_veyeral", "CHAR_storm_veyeral_left", "MOOD_sad"],
			"dialog"			: "В основном я нервничаю насчёт повторной встречи с Синей.",
		},
		{
			"character"			: ["VOICE_veyeral", "CHAR_storm_veyeral_left", "MOOD_normal"],
			"dialog"			: "Она такая    круглая, ну вы поняли?",
		},
	],
	
	"step1_ask_B_flip_flap" : [
		{
			"character"			: ["VOICE_flip_flap", "CHAR_flap_right", "MOOD_normal"],
			"dialog"			: "Столько |C3|[Чистого Негатива]|C0| вредно Вам.",
		},
		{
			"character"			: ["VOICE_veyeral", "CHAR_storm_veyeral_left", "MOOD_sad"],
			"dialog"			: "И что мне делать?",
		},
		{
			"character"			: ["VOICE_flip_flap", "CHAR_flip_right", "MOOD_normal"],
			"dialog"			: "|C3|[Чистый Негатив]|C0| плюс |C3|[Чистый Позитив]|C0| в сумме дают-",
		},
		{
			"character"			: ["VOICE_flip_flap", "CHAR_flap_right", "MOOD_happy"],
			"dialog"			: "|wave|Решение Вашей проблемы.",
		},
		{
			"character"			: ["VOICE_veyeral", "CHAR_storm_veyeral_left", "MOOD_normal"],
			"dialog"			: "Что это значит?",
		},
		{
			"character"			: ["VOICE_flip_flap", "CHAR_flip_right", "MOOD_happy"],
			"dialog"			: "Дайте Зарадене дар и негатив сократится.",
		},
	],
	"step1_leave_B_flip_flap" : [
		{
			"character"			: ["VOICE_veyeral", "CHAR_storm_veyeral_left", "MOOD_happy"],
			"dialog"			: "Никогда не думала, что Зарамехи будут помогать мне.",
		},
		{
			"character"			: ["VOICE_flip_flap", "CHAR_flip_right", "MOOD_happy"],
			"dialog"			: "Внутри Порождения Пустоты зарегистрирован |C3|[Чистый Позитив]|C0|.",
		},
		{
			"character"			: ["VOICE_flip_flap", "CHAR_flap_right", "MOOD_happy"],
			"dialog"			: "Этим Модулям больше нет нужды в |C3|[Чистом Негативе]|C0|.",
		},
	],
	"step1_leave_B_flip_flap_defect" : [
		{
			"character"			: ["VOICE_veyeral", "CHAR_storm_veyeral_left", "MOOD_happy"],
			"dialog"			: "Никогда не думала, что Зарамехи будут помогать мне.",
		},
		{
			"character"			: ["VOICE_flip_flap", "CHAR_flap_right", "MOOD_happy"],
			"dialog"			: "Мы узнали многое от существа из |C3|[Чистой Пустоты]|C0| и совершенства.",
		},
		{
			"character"			: ["VOICE_flip_flap", "CHAR_flip_right", "MOOD_blush"],
			"dialog"			: "Нет позитива в |shake|убийстве|norm| Порождения Пустоты.",
		},
		{
			"character"			: ["VOICE_veyeral", "CHAR_storm_veyeral_left", "MOOD_normal"],
			"dialog"			: "Она убедила Зарамехов быть с нами доброжелательной?",
		},
		{
			"character"			: ["VOICE_veyeral", "CHAR_storm_veyeral_left", "MOOD_happy"],
			"dialog"			: "Синяя Веераль действительно всесильна.",
		},
	],
	
	"step1_ask_B_sentinel_4x" : [
		{
			"character"			: ["VOICE_sentinel", "CHAR_sentinel_right", "MOOD_upset"],
			"dialog"			: "Стоять. Порождение Пустоты.",
		},
		{
			"character"			: ["VOICE_veyeral", "CHAR_storm_veyeral_left", "MOOD_normal"],
			"dialog"			: "|shake|Пожалуйста, не делай мне больно!",
		},
		{
			"character"			: ["VOICE_sentinel", "CHAR_sentinel_right", "MOOD_sad"],
			"dialog"			: "Этот Модуль не будет делать вам больно.",
		},
		{
			"character"			: ["VOICE_sentinel", "CHAR_sentinel_right", "MOOD_angry"],
			"dialog"			: "Если вы переживёте её викторину.",
		},
		{
			"character"			: ["VOICE_veyeral", "CHAR_storm_veyeral_left", "MOOD_normal"],
			"dialog"			: "|shake|Чё?",
		},
		{
			"character"			: ["VOICE_sentinel", "CHAR_sentinel_right", "MOOD_normal"],
			"dialog"			: "|C3|Вопрос 1:|C0| Получили ли вы сегодня любовь от Зарадены?",
		},
		{
			"character"			: ["VOICE_veyeral", "CHAR_storm_veyeral_left", "MOOD_normal"],
			"dialog"			: "Да? Как ты-",
		},
		{
			"love_hearts"		: 1,
			"character"			: ["VOICE_sentinel", "CHAR_sentinel_right", "MOOD_happy"],
			"dialog"			: "Правильный ответ.",
		},
		{
			"character"			: ["VOICE_sentinel", "CHAR_sentinel_right", "MOOD_normal"],
			"dialog"			: "|C3|Вопрос 2:|C0| Раскаиваетесь ли вы за своё поведение?",
		},
		{
			"character"			: ["VOICE_veyeral", "CHAR_storm_veyeral_left", "MOOD_sad"],
			"dialog"			: "Эмм... ну да.",
		},
		{
			"love_hearts"		: 1,
			"character"			: ["VOICE_sentinel", "CHAR_sentinel_right", "MOOD_happy"],
			"dialog"			: "Правильный ответ.",
		},
		{
			"character"			: ["VOICE_sentinel", "CHAR_sentinel_right", "MOOD_normal"],
			"dialog"			: "|C3|Вопрос 3:|C0| Поможете ли вы Этому Модулю доставить дар Зарадене?",
		},
		{
			"character"			: ["VOICE_veyeral", "CHAR_storm_veyeral_left", "MOOD_happy"],
			"dialog"			: "Да, помогу.",
		},
		{
			"love_hearts"		: 1,
			"character"			: ["VOICE_sentinel", "CHAR_sentinel_right", "MOOD_happy"],
			"dialog"			: "Правильный ответ.",
		},
		{
			"character"			: ["VOICE_sentinel", "CHAR_sentinel_right", "MOOD_normal"],
			"dialog"			: "|C3|Вопрос 4:|C0| Среди всех бонусных даров 1 ранга, какой больше всего понравится Зарадене?",
		},
	],
	
	
	"step1_ask_B_dot" : [
		{
			"character"			: ["VOICE_dot", "CHAR_dot_right", "MOOD_awkward"],
			"dialog"			: "Ты действительно думаешь, что она на тебя злится?|L|Даже после того, как ты обняла её?",
		},
		{
			"character"			: ["VOICE_veyeral", "CHAR_storm_veyeral_left", "MOOD_normal"],
			"dialog"			: "А мне надо было её обнять?",
		},
		{
			"character"			: ["VOICE_dot", "CHAR_dot_right", "MOOD_surprised"],
			"dialog"			: "Ты даже не попыталась?",
		},
		{
			"character"			: ["VOICE_veyeral", "CHAR_storm_veyeral_left", "MOOD_sad"],
			"dialog"			: "Нет.",
		},
		{
			"character"			: ["VOICE_veyeral", "CHAR_storm_veyeral_left", "MOOD_normal"],
			"dialog"			: "|shake|И что мне теперь делать?",
		},
		{
			"character"			: ["VOICE_dot", "CHAR_dot_right", "MOOD_happy"],
			"dialog"			: "Успокойся. Всё ещё можно исправить!",
		},
		{
			"character"			: ["VOICE_dot", "CHAR_dot_right", "MOOD_very_happy"],
			"dialog"			: "Просто опять найди её и отдай ей один из них.",
		},
	],
	
	
	"step1_ask_B_vitrea" : [
		{
			"love_hearts"		: 1,
			"character"			: ["VOICE_veyeral", "CHAR_storm_veyeral_left", "MOOD_happy"],
			"dialog"			: "Окей, это происходит опять, видимо.",
		},
		{
			"character"			: ["VOICE_vitrea", "CHAR_vitrea_right", "MOOD_blush"],
			"dialog"			: "Ничего не могу поделать!|L||shake|Ты просто такая милая!",
		},
		{
			"character"			: ["VOICE_vitrea", "CHAR_vitrea_right", "MOOD_happy_glare"],
			"dialog"			: "Сделана ли ты из электричества?",
		},
		{
			"character"			: ["VOICE_vitrea", "CHAR_vitrea_right", "MOOD_shocked_glare"],
			"dialog"			: "Как ты вообще работаешь?",
		},
		{
			"character"			: ["VOICE_veyeral", "CHAR_storm_veyeral_left", "MOOD_sad"],
			"dialog"			: "Эмм, я не знаю.",
		},
		{
			"character"			: ["VOICE_vitrea", "CHAR_vitrea_right", "MOOD_upset"],
			"dialog"			: "Ладно, забудь пока об этом.",
		},
		{
			"character"			: ["VOICE_vitrea", "CHAR_vitrea_right", "MOOD_content"],
			"dialog"			: "Я знаю, как сделать так, чтобы Зарадена простила тебя.",
		},
		{
			"character"			: ["VOICE_veyeral", "CHAR_storm_veyeral_left", "MOOD_sad"],
			"dialog"			: "И что мне делать?",
		},
		{
			"character"			: ["VOICE_vitrea", "CHAR_vitrea_right", "MOOD_happy_glare"],
			"dialog"			: "А ты знала, что Зараден легко победить, принося им дары?",
		},
		{
			"character"			: ["VOICE_vitrea", "CHAR_vitrea_right", "MOOD_aggressive"],
			"dialog"			: "Просто дай ей один из этих и она будет твоей подругой    |shake|навеки.",
		},
	],
	"step1_ask_B_vitrea_twins" : [
		{
			"love_hearts"		: 1,
			"character"			: ["VOICE_veyeral", "CHAR_storm_veyeral_left", "MOOD_happy"],
			"dialog"			: "Окей, это происходит опять, видимо.",
		},
		{
			"character"			: ["VOICE_vitrea", "CHAR_vitrea_right", "MOOD_blush"],
			"dialog"			: "Ничего не могу поделать!|L||shake|Ты просто такая милая!",
		},
		{
			"character"			: ["VOICE_veyeral", "CHAR_storm_veyeral_left", "MOOD_normal"],
			"dialog"			: "Всё как то, что мне пытались сказать те Зарадены.",
		},
		{
			"character"			: ["VOICE_veyeral", "CHAR_storm_veyeral_left", "MOOD_sad"],
			"dialog"			: "Но я не очень хорошо с ними обошлась.",
		},
		{
			"character"			: ["VOICE_vitrea", "CHAR_vitrea_right", "MOOD_content"],
			"dialog"			: "Ты всё ещё можешь исправить.",
		},
		{
			"character"			: ["VOICE_veyeral", "CHAR_storm_veyeral_left", "MOOD_sad"],
			"dialog"			: "И что мне делать?",
		},
		{
			"character"			: ["VOICE_vitrea", "CHAR_vitrea_right", "MOOD_happy_glare"],
			"dialog"			: "А ты знала, что Зараден легко победить, принося им дары?",
		},
		{
			"character"			: ["VOICE_vitrea", "CHAR_vitrea_right", "MOOD_aggressive"],
			"dialog"			: "Просто дай им один из этих и она будет твоей подругой    |shake|навеки.",
		},
	],
	"step1_leave_B_vitrea_defect" : [
		{
			"character"			: ["VOICE_vitrea", "CHAR_vitrea_right", "MOOD_glare"],
			"dialog"			: "А, ещё кое-что.",
		},
		{
			"character"			: ["VOICE_veyeral", "CHAR_storm_veyeral_left", "MOOD_happy"],
			"dialog"			: "И что же?",
		},
		{
			"character"			: ["VOICE_vitrea", "CHAR_vitrea_right", "MOOD_too_happy"],
			"dialog"			: "Стисни эту Синюю Веераль за меня!",
		},
		{
			"character"			: ["VOICE_veyeral", "CHAR_storm_veyeral_left", "MOOD_normal"],
			"dialog"			: "|shake|Что?!",
		},
		{
			"character"			: ["VOICE_vitrea", "CHAR_vitrea_right", "MOOD_shocked_glare"],
			"dialog"			: "Я забыла проверить ранее, и я должна знать, что произойдёт.",
		},
		{
			"character"			: ["VOICE_veyeral", "CHAR_storm_veyeral_left", "MOOD_sad"],
			"dialog"			: "Я даже не знаю, как я могу сделать это.",
		},
	],
	
	"step1_ask_B_pearl_twins" : [
		{
			"character"			: ["VOICE_pearl", "CHAR_pearl_right", "MOOD_happy"],
			"dialog"			: "...",
		},
		{
			"character"			: ["VOICE_veyeral", "CHAR_storm_veyeral_left", "MOOD_angry"],
			"dialog"			: "Хорошо! Я поняла!",
		},
		{
			"character"			: ["VOICE_veyeral", "CHAR_storm_veyeral_left", "MOOD_happy"],
			"dialog"			: "Я передам ей твои дары, окей?",
		},
		{
			"character"			: ["VOICE_pearl", "CHAR_pearl_tail_right", "MOOD_normal"],
			"dialog"			: "|C3|(Цветок очень возбуждённо покачивается.)",
		},
		{
			"character"			: ["VOICE_veyeral", "CHAR_storm_veyeral_left", "MOOD_happy"],
			"dialog"			: "Я всё ещё думаю, что однажды ты должна сделать это сама, но сегодня я тебе помогу.",
		},
	],
	"step1_leave_B_pearl_twins" : [
		{
			"character"			: ["VOICE_veyeral", "CHAR_storm_veyeral_left", "MOOD_normal"],
			"dialog"			: "Я скажу ей, что это от тебя, [VAL1].",
		},
		{
			"character"			: ["VOICE_veyeral", "CHAR_storm_veyeral_left", "MOOD_happy"],
			"dialog"			: "Это будет окей?",
		},
		{
			"love_hearts"		: 1,
			"character"			: ["VOICE_pearl", "CHAR_pearl_right", "MOOD_happy"],
			"dialog"			: "|C3|(Услышав это, Жемчужина обмякает и падает без сознания с улыбкой на лице.)",
		},
	],
	"step1_leave_B_pearl" : [
		{
			"character"			: ["VOICE_veyeral", "CHAR_storm_veyeral_left", "MOOD_happy"],
			"dialog"			: "Спасибо тебе за это!",
		},
		{
			"character"			: ["VOICE_veyeral", "CHAR_storm_veyeral_left", "MOOD_normal"],
			"dialog"			: "А, э... Как мне тебя звать?",
		},
		{
			"character"			: ["VOICE_pearl", "CHAR_pearl_right", "MOOD_happy"],
			"dialog"			: "|C3|(Она корябает |la||ris| в грязи.)",
		},
		{
			"character"			: ["VOICE_veyeral", "CHAR_storm_veyeral_left", "MOOD_happy"],
			"dialog"			: "Окей, [VAL1]! Можешь называть меня  \"[VAL2]\"-",
		},
		{
			"character"			: ["VOICE_veyeral", "CHAR_storm_veyeral_left", "MOOD_sad"],
			"dialog"			: "Ой, можешь его не произносить.",
		},
		{
			"love_hearts"		: 1,
			"character"			: ["VOICE_pearl", "CHAR_pearl_right", "MOOD_happy"],
			"dialog"			: "...",
		},
	],
	
	"step1_ask_B_momo" : [
		{
			"character"			: ["VOICE_veyeral", "CHAR_storm_veyeral_left", "MOOD_normal"],
			"dialog"			: "Какой красивый танец.",
		},
		{
			"character"			: ["VOICE_murder_blossom", "CHAR_murder_blossom_right", "MOOD_normal"],
			"dialog"			: "Обнаружен нарушитель.|L|Время убивать.",
		},
		{
			"character"			: ["VOICE_momo", "CHAR_momo_right", "MOOD_angry"],
			"dialog"			: "Назад, девочки!",
		},
		{
			"character"			: ["VOICE_momo", "CHAR_momo_right", "MOOD_confused"],
			"dialog"			: "Прости за них.",
		},
		{
			"character"			: ["VOICE_momo", "CHAR_momo_right", "MOOD_surprised"],
			"dialog"			: "Ты правда похвалила мой танец?|L|В тебе что-то изменилось.",
		},
		{
			"character"			: ["VOICE_momo", "CHAR_momo_right", "MOOD_confused"],
			"dialog"			: "Не повстречалась ли тебе сегодня Зарадена?",
		},
		{
			"character"			: ["VOICE_veyeral", "CHAR_storm_veyeral_left", "MOOD_sad"],
			"dialog"			: "Да, мы виделись.",
		},
		{
			"character"			: ["VOICE_momo", "CHAR_momo_right", "MOOD_sad"],
			"dialog"			: "Хорошо понимаю, что ты чувствуешь.",
		},
		{
			"character"			: ["VOICE_momo", "CHAR_momo_right", "MOOD_confused"],
			"dialog"			: "Я уже собиралась отправить цветки с дарами к Зарадене.",
		},
		{
			"character"			: ["VOICE_momo", "CHAR_momo_right", "MOOD_happy"],
			"dialog"			: "Но, наверное, лучше вместо этого доставь их ты!",
		},
	],
	
	"step1_ask_B_split_veyeral_defect" : [
		{
			"character"			: ["VOICE_veyeral", "CHAR_veyeral_right", "MOOD_happy"],
			"dialog"			: "Так ты тоже встретила Синюю Веераль?",
		},
		{
			"character"			: ["VOICE_veyeral", "CHAR_storm_veyeral_left", "MOOD_sad"],
			"dialog"			: "Да, я встретила, но я типа напала на её подругу.",
		},
		{
			"character"			: ["VOICE_veyeral", "CHAR_multi_veyeral_right", "MOOD_sad"],
			"dialog"			: "Мы    тоже так поступили.",
		},
		{
			"character"			: ["VOICE_veyeral", "CHAR_storm_veyeral_left", "MOOD_normal"],
			"dialog"			: "Из-за этого я чувствую себя ужасно.",
		},
		{
			"character"			: ["VOICE_veyeral", "CHAR_veyeral_right", "MOOD_happy"],
			"dialog"			: "Знаю, давай дадим ей дар из наших закромов!",
		},
	],
	
	"step1_ask_B_frozen_veyeral_devil" : [
		{
			"character"			: ["VOICE_veyeral", "CHAR_storm_veyeral_left", "MOOD_normal"],
			"dialog"			: "Так ты тоже встретила эту Зарадену?|L||!|Ту, что зовёт себя Дьявол?",
		},
		{
			"character"			: ["VOICE_veyeral", "CHAR_frozen_veyeral_right", "MOOD_happy"],
			"dialog"			: "В ней было столько тепла!",
		},
		{
			"character"			: ["VOICE_veyeral", "CHAR_frozen_veyeral_right", "MOOD_normal"],
			"dialog"			: "Несмотря на то, что я была холодна к ней, она держала меня так крепко.",
		},
		{
			"character"			: ["VOICE_veyeral", "CHAR_frozen_veyeral_right", "MOOD_sad"],
			"dialog"			: "Хотелось бы, чтобы она меня никогда не отпускала.",
		},
		{
			"character"			: ["VOICE_veyeral", "CHAR_storm_veyeral_left", "MOOD_happy"],
			"dialog"			: "|wave|Тебе она очень нравится.",
		},
		{
			"character"			: ["VOICE_veyeral", "CHAR_frozen_veyeral_right", "MOOD_sad"],
			"dialog"			: "Эй, если ты её ещё увидишь...",
		},
		{
			"character"			: ["VOICE_veyeral", "CHAR_frozen_veyeral_right", "MOOD_normal"],
			"dialog"			: "Не против отнести ей эти дары?",
		},
	],
	"step1_leave_B_frozen_veyeral_devil" : [
		{
			"character"			: ["VOICE_veyeral", "CHAR_storm_veyeral_left", "MOOD_happy"],
			"dialog"			: "Я скажу ей, что это от тебя.",
		},
		{
			"character"			: ["VOICE_veyeral", "CHAR_frozen_veyeral_right", "MOOD_sad"],
			"dialog"			: "Это можно...",
		},
		{
			"character"			: ["VOICE_veyeral", "CHAR_frozen_veyeral_right", "MOOD_normal"],
			"dialog"			: "Почему мне теперь так тепло?",
		},
		{
			"love_hearts"		: 1,
			"character"			: ["VOICE_veyeral", "CHAR_frozen_veyeral_right", "MOOD_happy"],
			"dialog"			: "|shake|Что со мной не так?",
		},
	],
	
	
	

	
	"step2_intro_generic" : [
		{
			"character"			: ["VOICE_veyeral", "CHAR_storm_veyeral_right", "MOOD_sad"],
			"random"			: 3,
			"dialog_rand1"		: "|shake|Эмм,   мисс Зарадена?",
			"dialog_rand2"		: "|shake|П-привет,    я тебя искала.",
			"dialog_rand3"		: "|shake|Ты помнишь меня,   да?",
		},
		{
			"character"			: ["VOICE_veyeral", "CHAR_storm_veyeral_right", "MOOD_normal"],
			"dialog"			: "|shake|Извини меня!",
		},
		{
			"character"			: ["VOICE_veyeral", "CHAR_storm_veyeral_right", "MOOD_sad"],
			"dialog"			: "Я не должна была нападать на тебя ранее.",
		},
	],
	"step2_intro_single" : [
		{
			"character"			: ["VOICE_veyeral", "CHAR_storm_veyeral_right", "MOOD_sad"],
			"random"			: 3,
			"dialog_rand1"		: "Эмм, [VAL1] сказала мне, что я должна отдать тебе это.",
			"dialog_rand2"		: "Я принесла тебе дар.|L|Ну, на самом деле, его передаёт тебе [VAL1].",
			"dialog_rand3"		: "[VAL1] подумала, что если дать тебе это, то-   |L|Я не знаю.",
		},
	],
	"step2_intro_multi" : [
		{
			"character"			: ["VOICE_veyeral", "CHAR_storm_veyeral_right", "MOOD_sad"],
			"random"			: 3,
			"dialog_rand1"		: "[VAL1] хотела, чтобы я отдала их тебе.",
			"dialog_rand2"		: "Я принесла тебе дары.|L|Ну, на самом деле, [VAL1] сказала вам их отдать.",
			"dialog_rand3"		: "[VAL1] подумала, что если дать вам эти дары, то-   |L|Я не знаю.",
		},
	],
	"step2_intro_B_storm_veyeral"		: "step2_intro_self",
	"step2_intro_B_anomaly"				: "step2_intro_self",
	"step2_intro_self" 	: [
		{
			"character"			: ["VOICE_veyeral", "CHAR_storm_veyeral_right", "MOOD_sad"],
			"dialog"			: "|shake|Эмм,   мисс Зарадена?",
		},
		{
			"character"			: ["VOICE_veyeral", "CHAR_storm_veyeral_right", "MOOD_normal"],
			"dialog"			: "Я, ахх,    принесла тебе дар.",
		},
		{
			"character"			: ["VOICE_veyeral", "CHAR_storm_veyeral_right", "MOOD_sad"],
			"dialog"			: "Я просто хотела сказать-",
		},
		{
			"character"			: ["VOICE_veyeral", "CHAR_storm_veyeral_right", "MOOD_normal"],
			"dialog"			: "|shake|Извини за то, что напала на тебя!",
		},
	],
	"step2_intro_B_boiler"				: "step2_intro_worry",
	"step2_intro_B_amalga"				: "step2_intro_worry",
	"step2_intro_worry" 	: [
		{
			"character"			: ["VOICE_veyeral", "CHAR_storm_veyeral_right", "MOOD_sad"],
			"dialog"			: "Эмм,   [VAL1] хотела, чтобы я передала тебе это.",
		},
		{
			"character"			: ["VOICE_veyeral", "CHAR_storm_veyeral_right", "MOOD_normal"],
			"dialog"			: "Она о тебе прям беспокоится, ты знаешь?",
		},
		{
			"character"			: ["VOICE_veyeral", "CHAR_storm_veyeral_right", "MOOD_sad"],
			"dialog"			: "А ещё, я просто хотела сказать-",
		},
		{
			"character"			: ["VOICE_veyeral", "CHAR_storm_veyeral_right", "MOOD_normal"],
			"dialog"			: "|shake|Извини, что раннее напала на тебя!",
		},
	],
	"step2_intro_B_blot_blank"			: "step2_intro_crush",
	"step2_intro_B_calorie_twins"		: "step2_intro_crush",
	"step2_intro_B_heliola_twins"		: "step2_intro_crush",
	"step2_intro_B_chemory_blank"		: "step2_intro_crush",
	"step2_intro_B_chemory_twins"		: "step2_intro_crush",
	"step2_intro_B_astrayo_twins"		: "step2_intro_crush",
	"step2_intro_B_philolu"				: "step2_intro_crush",
	"step2_intro_B_frozen_veyeral_devil": "step2_intro_crush",
	"step2_intro_crush" 	: [
		{
			"character"			: ["VOICE_veyeral", "CHAR_storm_veyeral_right", "MOOD_sad"],
			"dialog"			: "Я всего лишь хотела    извиниться за нападение на тебя.",
		},
		{
			"character"			: ["VOICE_veyeral", "CHAR_storm_veyeral_right", "MOOD_normal"],
			"dialog"			: "Но я принесла кое что, что тебе понравится!",
		},
		{
			"character"			: ["VOICE_veyeral", "CHAR_storm_veyeral_right", "MOOD_happy"],
			"dialog"			: "[VAL1] |wave|очень|norm| хотела тебе передать их.",
		},
		{
			"character"			: ["VOICE_veyeral", "CHAR_storm_veyeral_right", "MOOD_happy"],
			"dialog"			: "Она была |wave|очень, очень рада|norm|, когда говорила о тебе.",
		},
	],
	"step2_intro_B_pearl_twins" 	: [
		{
			"character"			: ["VOICE_veyeral", "CHAR_storm_veyeral_right", "MOOD_normal"],
			"dialog"			: "Я принесла тебе то, что тебе понравится!",
		},
		{
			"character"			: ["VOICE_veyeral", "CHAR_storm_veyeral_right", "MOOD_happy"],
			"dialog"			: "[VAL1] |wave|очень|norm| хотела, чтобы я дала это тебе.",
		},
		{
			"character"			: ["VOICE_veyeral", "CHAR_storm_veyeral_right", "MOOD_happy"],
			"dialog"			: "Она была |wave|очень-очень счастлива|norm|, когда говорила с тобой.",
		},
		{
			"character"			: ["VOICE_veyeral", "CHAR_storm_veyeral_right", "MOOD_sad"],
			"dialog"			: "Не то чтобы говорила, но-",
		},
		{
			"character"			: ["VOICE_veyeral", "CHAR_storm_veyeral_right", "MOOD_happy"],
			"dialog"			: "Ну, ты понимаешь, о чём я.",
		},
	],
	"comment_delivery_single"	: {
		"character"	: ["VOICE_veyeral", "CHAR_storm_veyeral_right", "MOOD_normal"],
		"dialog"	: "Пожалуйста, возьми его.",
	},
	"comment_delivery_multi"	: {
		"character"	: ["VOICE_veyeral", "CHAR_storm_veyeral_right", "MOOD_happy"],
		"dialog"	: "Все они для тебя!",
	},
	"step2_another_gift" 	: [
		{
			"character"			: ["VOICE_veyeral", "CHAR_storm_veyeral_right", "MOOD_happy"],
			"dialog"			: "Другой тоже для тебя.",
		},
	],
	
	"step2_leave_blank" 	: [
		{
			"character"			: ["VOICE_blank", "CHAR_blank_left", "MOOD_normal"],
			"dialog"			: "Ты всё ещё должна сделать ещё кое-что для меня.",
		},
		{
			"character"			: ["VOICE_blank", "CHAR_blank_left", "MOOD_happy"],
			"dialog"			: "[VAL1] должна услышать от тебя \"Я люблю тебя!\"|L||!|И ещё-",
		},
		{
			"character"			: ["VOICE_blank", "CHAR_blank_left", "MOOD_very_happy"],
			"dialog"			: "|wave|Я люблю тебя!",
		},
		{
			"love_hearts"		: 1,
			"character"			: ["VOICE_veyeral", "CHAR_storm_veyeral_right", "MOOD_happy"],
			"dialog"			: "Я посмотрю, что я смогу сделать.",
		},
	],
	"step2_leave_defect" 	: [
		{
			"character"			: ["VOICE_defect", "CHAR_defect_left", "MOOD_normal"],
			"dialog"			: "[VAL1]? Передай ей \"Спасибо!\"",
		},
		{
			"character"			: ["VOICE_veyeral", "CHAR_storm_veyeral_right", "MOOD_sad"],
			"dialog"			: "Так ты меня прощаешь?",
		},
		{
			"character"			: ["VOICE_veyeral", "CHAR_blue_veyeral_left", "MOOD_normal"],
			"dialog"			: "Ты прощена, моя буревая сестра.",
		},
		{
			"character"			: ["VOICE_veyeral", "CHAR_blue_veyeral_left", "MOOD_happy"],
			"dialog"			: "Ты и не могла знать, что твой оппонент будет |wave|идеален.",
		},
	],
	"step2_leave_twins" 	: [
		{
			"character"			: ["VOICE_ryden", "CHAR_ryden_left", "MOOD_happy"],
			"dialog"			: "Больше даров от твоих девушек, Солнышко?",
		},
		{
			"character"			: ["VOICE_xaila", "CHAR_xaila_left", "MOOD_suspicious"],
			"dialog"			: "Это не так.",
		},
		{
			"character"			: ["VOICE_veyeral", "CHAR_storm_veyeral_right", "MOOD_sad"],
			"dialog"			: "Мы не друзья?",
		},
		{
			"character"			: ["VOICE_xaila", "CHAR_xaila_left", "MOOD_surprised_blush"],
			"dialog"			: "|shake|Нет, погоди!|norm|    Это ТАК.   |L|В смысле-",
		},
		{
			"character"			: ["VOICE_xaila", "CHAR_xaila_left", "MOOD_pain"],
			"dialog"			: "|shake|Зелёнка!",
		},
	],
	"step2_leave_devil" 	: [
		{
			"character"			: ["VOICE_devil", "CHAR_devil_left", "MOOD_happy"],
			"dialog"			: "Не за что извиняться, моя буревая подруга.",
		},
		{
			"character"			: ["VOICE_devil", "CHAR_devil_left", "MOOD_aggressive2"],
			"dialog"			: "Наша великая битва была предсказана в легендах!",
		},
		{
			"character"			: ["VOICE_veyeral", "CHAR_storm_veyeral_right", "MOOD_normal"],
			"dialog"			: "Правда?",
		},
		{
			"character"			: ["VOICE_devil", "CHAR_devil_left", "MOOD_serious2"],
			"dialog"			: "Битва была воистину праведной, её никак нельзя было предотвратить.",
		},
	],
	"step2_leave_default" : [
		{
			"character"			: ["VOICE_veyeral", "CHAR_storm_veyeral_right", "MOOD_normal"],
			"dialog"			: "Ты простишь меня?",
		},
		{
			"love_hearts"		: 1,
			"character"			: ["VOICE_veyeral", "CHAR_storm_veyeral_right", "MOOD_happy"],
			"dialog"			: "Я приму это за \"да\"",
		},
	],
	"step2_leave_B_storm_veyeral_blank"		: "step2_leave_self",
	"step2_leave_B_storm_veyeral_defect"	: "step2_leave_self",
	"step2_leave_B_anomaly_blank"			: "step2_leave_self",
	"step2_leave_B_anomaly_defect"			: "step2_leave_self",
	"step2_leave_self_blank" 	: [
		{
			"character"			: ["VOICE_blank", "CHAR_blank_left", "MOOD_confused"],
			"dialog"			: "Ты не обязана была это делать.",
		},
		{
			"character"			: ["VOICE_blank", "CHAR_blank_left", "MOOD_content"],
			"dialog"			: "Но я знаю, что тебе это было очень тяжело.",
		},
		{
			"character"			: ["VOICE_blank", "CHAR_blank_left", "MOOD_happy"],
			"dialog"			: "|wave|Я люблю тебя!",
		},
		{
			"love_hearts"		: 1,
			"character"			: ["VOICE_veyeral", "CHAR_storm_veyeral_right", "MOOD_happy"],
			"dialog"			: "О, это было так просто?",
		},
	],
	"step2_leave_self_defect" 	: [
		{
			"character"			: ["VOICE_defect", "CHAR_defect_left", "MOOD_surprised"],
			"dialog"			: "Ты искала меня, просто чтобы извиниться?",
		},
		{
			"character"			: ["VOICE_veyeral", "CHAR_storm_veyeral_right", "MOOD_sad"],
			"dialog"			: "Да?",
		},
		{
			"character"			: ["VOICE_defect", "CHAR_defect_left", "MOOD_blush"],
			"dialog"			: "О,   ээ-|L||!|Не беспокойся?",
		},
		{
			"character"			: ["VOICE_defect", "CHAR_defect_left", "MOOD_confused_blush"],
			"dialog"			: "Я не знаю, что и сказать.",
		},
		{
			"character"			: ["VOICE_veyeral", "CHAR_blue_veyeral_left", "MOOD_happy"],
			"dialog"			: "Моя дорогуша Дефект вышла из строя из-за новых чувств.",
		},
	],
	"step2_leave_B_scrambla_defect"			: "step2_leave_crush",
	"step2_leave_B_blot_blank"				: "step2_leave_crush",
	"step2_leave_B_calorie_twins"			: "step2_leave_crush",
	"step2_leave_B_heliola_twins"			: "step2_leave_crush",
	"step2_leave_B_chemory_blank"			: "step2_leave_crush",
	"step2_leave_B_chemory_twins"			: "step2_leave_crush",
	"step2_leave_B_astrayo_twins"			: "step2_leave_crush",
	"step2_leave_B_philolu"					: "step2_leave_crush",
	"step2_leave_B_pearl_twins"				: "step2_leave_crush",
	"step2_leave_B_frozen_veyeral_devil"	: "step2_leave_crush",
	"step2_leave_crush_blank" 	: [
		{
			"character"			: ["VOICE_blank", "CHAR_blank_left", "MOOD_confused_blush"],
			"dialog"			: "Когда ты сказала, что она была \"очень, очень\" рада-",
		},
		{
			"character"			: ["VOICE_veyeral", "CHAR_storm_veyeral_right", "MOOD_happy"],
			"dialog"			: "Я скажу прямо!|L|Она в тебя влюбилась!",
		},
		{
			"character"			: ["VOICE_blank", "CHAR_blank_left", "MOOD_sad_blush"],
			"dialog"			: "О, [VAL1]...",
		},
		{
			"character"			: ["VOICE_veyeral", "CHAR_storm_veyeral_right", "MOOD_sad"],
			"dialog"			: "Я вижу...",
		},
		{
			"character"			: ["VOICE_veyeral", "CHAR_storm_veyeral_right", "MOOD_normal"],
			"dialog"			: "Мне кажется, ты сделала её счастливее, что бы не произойдёт.",
		},
		{
			"character"			: ["VOICE_blank", "CHAR_blank_left", "MOOD_content"],
			"dialog"			: "Спасибо, что сказала это.|L|Я люблю тебя, [VAL3].",
		},
		{
			"love_hearts"		: 1,
			"character"			: ["VOICE_veyeral", "CHAR_storm_veyeral_right", "MOOD_happy"],
			"dialog"			: "Мне кажется, я говорю за всех нас, когда я говорю,   мы тоже тебя любим.",
		},
	],
	"step2_leave_crush_defect" 	: [
		{
			"character"			: ["VOICE_defect", "CHAR_defect_left", "MOOD_content"],
			"dialog"			: "[VAL1] выслушает от меня комплименты позже.",
		},
		{
			"character"			: ["VOICE_defect", "CHAR_defect_left", "MOOD_confused"],
			"dialog"			: "Но почему она не принесла мне их сама?",
		},
		{
			"character"			: ["VOICE_veyeral", "CHAR_storm_veyeral_right", "MOOD_happy"],
			"dialog"			: "|wave|Ну,|norm|   я думаю-",
		},
		{
			"character"			: ["VOICE_veyeral", "CHAR_blue_veyeral_left", "MOOD_normal"],
			"dialog"			: "Всё ещё хуже, чем я думала.|!||L|Она была воистину поражена моей идеальной формой.",
		},
		{
			"character"			: ["VOICE_veyeral", "CHAR_blue_veyeral_left", "MOOD_happy"],
			"dialog"			: "Придётся мягко ей отказать.",
		},
	],
	"step2_leave_crush_twins" 	: [
		{
			"character"			: ["VOICE_ryden", "CHAR_ryden_left", "Mood_suspicious2"],
			"dialog"			: "[VAL1] |wave|прям-прям|norm| хотела, чтобы это было у Солнышка?",
		},
		{
			"character"			: ["VOICE_veyeral", "CHAR_storm_veyeral_right", "MOOD_happy"],
			"dialog"			: "|wave|ПРЯМ-прям-прям.",
		},
		{
			"character"			: ["VOICE_ryden", "CHAR_ryden_left", "MOOD_happy"],
			"dialog"			: "Ооо, |wave|прям так?",
		},
		{
			"character"			: ["VOICE_xaila", "CHAR_xaila_left", "MOOD_surprised_blush"],
			"dialog"			: "Что всё это значит?",
		},
		{
			"character"			: ["VOICE_ryden", "CHAR_ryden_left", "MOOD_very_happy"],
			"dialog"			: "|wave|Да ничего, Солнышко.",
		},
	],
	"step2_leave_crush_devil" 	: [
		{
			"character"			: ["VOICE_devil", "CHAR_devil_left", "MOOD_serious2"],
			"dialog"			: "Итак, ещё одна становится жертвой моего дьвольского обаяния. Я права?",
		},
		{
			"character"			: ["VOICE_veyeral", "CHAR_storm_veyeral_right", "MOOD_happy"],
			"dialog"			: "Мне прям так кажется.",
		},
		{
			"character"			: ["VOICE_devil", "CHAR_devil_left", "MOOD_content"],
			"dialog"			: "Такие случаи нередки.",
		},
		{
			"character"			: ["VOICE_devil", "CHAR_devil_left", "MOOD_sad2"],
			"dialog"			: "Увы, Дьявол может выбрать только одну.",
		},
		{
			"character"			: ["VOICE_devil", "CHAR_devil_left", "MOOD_confused"],
			"dialog"			: "Но я не могу решать всё это, пока я занимаюсь группой.",
		},
		{
			"character"			: ["VOICE_devil", "CHAR_devil_left", "MOOD_pain"],
			"dialog"			: "|shake|И почему я такая обаятельная?",
		},
		{
			"character"			: ["VOICE_veyeral", "CHAR_storm_veyeral_right", "MOOD_sad"],
			"dialog"			: "Тебе, наверное, так тяжело.",
		},
	],
	
	
	"step2_intro_B_scrambla_defect" 	: [
		{
			"character"			: ["VOICE_veyeral", "CHAR_storm_veyeral_right", "MOOD_happy"],
			"dialog"			: "Мисс Зарадена? Ты знаешь Осколок по имени [VAL1]?",
		},
		{
			"character"			: ["VOICE_defect", "CHAR_defect_left", "MOOD_normal"],
			"dialog"			: "Я знаю её. А что?",
		},
		{
			"character"			: ["VOICE_veyeral", "CHAR_storm_veyeral_right", "MOOD_happy"],
			"dialog"			: "Она |wave|очень|norm|    хотела отдать тебе их.",
		},
		{
			"character"			: ["VOICE_defect", "CHAR_defect_left", "MOOD_surprised"],
			"dialog"			: "Отдать мне, взаправду?",
		},
	],
	
	"step2_intro_B_monovai" : [
		{
			"character"			: ["VOICE_veyeral", "CHAR_storm_veyeral_right", "MOOD_normal"],
			"dialog"			: "|shake|Прости меня!",
		},
		{
			"character"			: ["VOICE_veyeral", "CHAR_storm_veyeral_right", "MOOD_sad"],
			"dialog"			: "Я не должна была тебя атаковать тогда.",
		},
		{
			"character"			: ["VOICE_veyeral", "CHAR_storm_veyeral_right", "MOOD_sad"],
			"dialog"			: "Эмм, [VAL1] сказала, что я должна дать это тебе.",
		},
		{
			"character"			: ["VOICE_veyeral", "CHAR_storm_veyeral_right", "MOOD_normal"],
			"dialog"			: "Я правда не понимаю, о чём она говорит большую часть времени.",
		},
		{
			"character"			: ["VOICE_veyeral", "CHAR_storm_veyeral_right", "MOOD_happy"],
			"dialog"			: "Но, похоже, стоило это сделать.",
		},
	],
	
	"step2_leave_B_philolu_twins" 	: [
		{
			"character"			: ["VOICE_ryden", "CHAR_ryden_left", "MOOD_happy"],
			"dialog"			: "|wave|Ну,   как свидание с [VAL1]?",
		},
		{
			"character"			: ["VOICE_veyeral", "CHAR_storm_veyeral_right", "MOOD_normal"],
			"dialog"			: "Разве было свидание?",
		},
		{
			"character"			: ["VOICE_xaila", "CHAR_xaila_left", "MOOD_serious2"],
			"dialog"			: "Я только запомнила, что моя сестра оставила меня.",
		},
		{
			"character"			: ["VOICE_ryden", "CHAR_ryden_left", "MOOD_shocked"],
			"dialog"			: "|shake|Нет!|L|Это не-|L|Я не-",
		},
		{
			"character"			: ["VOICE_ryden", "CHAR_ryden_left", "MOOD_pain"],
			"dialog"			: "|shake|Я люблю тебя, Солнышко!",
		},
		{
			"love_hearts"		: 1,
			"character"			: ["VOICE_xaila", "CHAR_xaila_left", "MOOD_content"],
			"dialog"			: "...",
		},
	],
	
	"step2_leave_B_vitrea_defect" 	: [
		{
			"character"			: ["VOICE_veyeral", "CHAR_storm_veyeral_right", "MOOD_sad"],
			"dialog"			: "О, и ещё...",
		},
		{
			"character"			: ["VOICE_veyeral", "CHAR_storm_veyeral_right", "MOOD_sad"],
			"dialog"			: "Эмм...",
		},
		{
			"love_hearts"		: 1,
			"character"			: ["VOICE_veyeral", "CHAR_blue_veyeral_left", "MOOD_happy"],
			"dialog"			: "Ну, это было неожиданно!",
		},
		{
			"character"			: ["VOICE_veyeral", "CHAR_storm_veyeral_right", "MOOD_sad"],
			"dialog"			: "[VAL1] попросила меня сжать тебя как можно сильнее и посмотреть, что получится.",
		},
		{
			"character"			: ["VOICE_veyeral", "CHAR_storm_veyeral_right", "MOOD_normal"],
			"dialog"			: "Что-нибудь получилось?",
		},
		{
			"character"			: ["VOICE_veyeral", "CHAR_blue_veyeral_left", "MOOD_normal"],
			"dialog"			: "Хмм, Я не могу стать ещё более идеальной.",
		},
		{
			"character"			: ["VOICE_veyeral", "CHAR_blue_veyeral_left", "MOOD_normal"],
			"dialog"			: "Может быть, вместо этого что-то случилось с тобой?",
		},
		{
			"character"			: ["VOICE_veyeral", "CHAR_storm_veyeral_right", "MOOD_happy"],
			"dialog"			: "Ну, было очень приятно находиться так близко к тебе.",
		},
		{
			"love_hearts"		: 1,
			"character"			: ["VOICE_veyeral", "CHAR_blue_veyeral_left", "MOOD_happy"],
			"dialog"			: "Должно быть, тебе передалась частичка идеала.",
			},
	],
	
}
